outlookbot/__init__.py
outlookbot/__main__.py
outlookbot/cli.py
outlookbot/config.py
outlookbot/data_file_utils.py
outlookbot/email_template.py
outlookbot/outlook_client.py
outlookbot/setup_utils.py
outlookbot-0.0.2.dist-info/METADATA
outlookbot-0.0.2.dist-info/WHEEL
outlookbot-0.0.2.dist-info/entry_points.txt
outlookbot-0.0.2.dist-info/top_level.txt
outlookbot-0.0.2.dist-info/RECORD
